{
  "education": [
    {
      "institution": "The University of Tokyo",
      "location": "Tokyo, Japan",
      "studyType": "Master in Computer Science",
      "startDate": "2023",
      "endDate": "2025"
    },
    {
      "institution": "Peking University",
      "location": "Beijing, China",
      "studyType": "Bachelor in Robotics",
      "startDate": "2019",
      "endDate": "2023"
    }
  ],
  "languages": [
    {
      "language": "Chinese (Mandarin)",
      "fluency": "Native",
      "icon": ""
    },
    {
      "language": "English",
      "fluency": "Proficient",
      "icon": ""
    },
    {
      "language": "Japanese",
      "fluency": "Basic",
      "icon": ""
    },
    {
      "language": "German",
      "fluency": "Intermediate (reading)",
      "icon": ""
    }
  ]
}
